[  
    {  
        "id":0,
        "tipo_despacho":"Penal",
        "nombre_despacho":[  
            "Juez 01 penal municipal Palmira",
            "Juez 02 penal municipal Palmira",
            "Juez 03 penal municipal Palmira",
            "Juez 04 penal municipal Palmira",
            "Juez 05 penal municipal Palmira",
            "Juez 06 penal municipal Palmira",
            "Juez 07 penal municipal Palmira",
            "Juez 08 penal municipal Palmira",
            "Juez 01 penal circuito Palmira",
            "Juez 02 penal circuito Palmira",
            "Juez 03 penal circuito Palmira",
            "Juez 04 penal circuito Palmira",
            "Juez 05 penal circuito Palmira",
            "Juez 06 penal circuito Palmira",
            "Juez 07 penal circuito Palmira",
            "Juez 08 penal circuito Palmira",
            "Juez 01 penal municipal Cali", 
            "Juez 02 penal municipal Cali",
            "Juez 03 penal municipal Cali", 
            "Juez 04 penal municipal Cali",
            "Juez 05 penal municipal Cali", 
            "Juez 06 penal municipal Cali",
            "Juez 07 penal municipal Cali", 
            "Juez 08 penal municipal Cali",
            "Juez 09 penal municipal Cali", 
            "Juez 10 penal municipal Cali",
            "Juez 11 penal municipal Cali", 
            "Juez 12 penal municipal Cali",
            "Juez 13 penal municipal Cali", 
            "Juez 14 penal municipal Cali",
            "Juez 15 penal municipal Cali", 
            "Juez 16 penal municipal Cali",
            "Juez 17 penal municipal Cali",
            "Juez 18 penal municipal Cali", 
            "Juez 19 penal municipal Cali",
            "Juez 20 penal municipal Cali", 
            "Juez 21 penal municipal Cali",
            "Juez 22 penal municipal Cali", 
            "Juez 23 penal municipal Cali",
            "Juez 01 penal circuito Cali", 
            "Juez 02 penal circuito Cali",
            "Juez 03 penal circuito Cali", 
            "Juez 04 penal circuito Cali",
            "Juez 05 penal circuito Cali", 
            "Juez 06 penal circuito Cali",
            "Juez 07 penal circuito Cali", 
            "Juez 08 penal circuito Cali",
            "Juez 09 penal circuito Cali", 
            "Juez 10 penal circuito Cali",
            "Juez 11 penal circuito Cali", 
            "Juez 12 penal circuito Cali",
            "Juez 13 penal circuito Cali", 
            "Juez 14 penal circuito Cali",
            "Juez 15 penal circuito Cali", 
            "Juez 16 penal circuito Cali",
            "Juez 17 penal circuito Cali",
            "Juez 18 penal circuito Cali", 
            "Juez 19 penal circuito Cali",
            "Juez 20 penal circuito Cali", 
            "Juez 22 penal circuito Cali",
            "Juez 23 penal circuito Cali",
            "Juez 01 penal municipal Buga",
            "Juez 02 penal municipal Buga",
            "Juez 03 penal municipal Buga",
            "Juez 04 penal municipal Buga",
            "Juez 05 penal municipal Buga",
            "Juez 06 penal municipal Buga",
            "Juez 01 penal circuito Buga",
            "Juez 02 penal circuito Buga",
            "Juez 03 penal circuito Buga",
            "Juez 04 penal circuito Buga",
            "Juez 01 penal circuito especializado Buga",
            "Juez 02 penal circuito especializado Buga",
            "Juez 03 penal circuito especializado Buga",
            "Juez 04 penal circuito especializado Buga"  
        ]
    },
    {  
        "id":1,
        "tipo_despacho":"Civil",
        "nombre_despacho":[  
            "Juez 01 civil municipal Palmira",
            "Juez 02 civil municipal Palmira",
            "Juez 03 civil municipal Palmira",
            "Juez 04 civil municipal Palmira",
            "Juez 05 civil municipal Palmira",
            "Juez 06 civil municipal Palmira",
            "Juez 01 civil circuito Palmira",
            "Juez 02 civil circuito Palmira",
            "Juez 03 civil circuito Palmira",
            "Juez 04 civil circuito Palmira",
            "Juez 05 civil circuito Palmira",
            "Juez 06 civil circuito Palmira",
            "Juez 01 civil municipal Cali",
            "Juez 02 civil municipal Cali",
            "Juez 03 civil municipal Cali",
            "Juez 04 civil municipal Cali",
            "Juez 05 civil municipal Cali",
            "Juez 06 civil municipal Cali",
            "Juez 01 civil circuito Cali",
            "Juez 02 civil circuito Cali",
            "Juez 03 civil circuito Cali",
            "Juez 04 civil circuito Cali",
            "Juez 05 civil circuito Cali",
            "Juez 06 civil circuito Cali",
            "Juez 01 civil municipal Cali",
            "Juez 02 civil municipal Cali",
            "Juez 03 civil municipal Cali",
            "Juez 04 civil municipal Cali",
            "Juez 05 civil municipal Cali",
            "Juez 06 civil municipal Cali",
            "Juez 01 civil circuito Cali",
            "Juez 02 civil circuito Cali",
            "Juez 03 civil circuito Cali",
            "Juez 04 civil circuito Cali",
            "Juez 05 civil circuito Cali",
            "Juez 06 civil circuito Cali",
            "Juez 01 civil municipal Buga",
            "Juez 02 civil municipal Buga",
            "Juez 03 civil municipal Buga",
            "Juez 04 civil municipal Buga",
            "Juez 01 civil circuito Buga",
            "Juez 02 civil circuito Buga",
            "Juez 03 civil circuito Buga",
            "Juez 04 civil circuito Buga"         
        ]
    },
    {  
        "id":2,
        "tipo_despacho":"Familia",
        "nombre_despacho":[  
            "Juez 01 familia municipal Palmira",
            "Juez 02 familia municipal Palmira",
            "Juez 03 familia municipal Palmira",
            "Juez 04 familia municipal Palmira",
            "Juez 05 familia municipal Palmira",
            "Juez 06 familia municipal Palmira",
            "Juez 01 familia circuito Palmira",
            "Juez 02 familia circuito Palmira",
            "Juez 03 familia circuito Palmira",
            "Juez 04 familia circuito Palmira",
            "Juez 05 familia circuito Palmira",
            "Juez 06 familia circuito Palmira",
            "Juez 01 familia municipal Cali",
            "Juez 02 familia municipal Cali",
            "Juez 03 familia municipal Cali",
            "Juez 04 familia municipal Cali",
            "Juez 05 familia municipal Cali",
            "Juez 06 familia municipal Cali",
            "Juez 01 familia circuito Cali",
            "Juez 02 familia circuito Cali",
            "Juez 03 familia circuito Cali",
            "Juez 04 familia circuito Cali",
            "Juez 05 familia circuito Cali",
            "Juez 06 familia circuito Cali",
            "Juez 01 familia municipal Cali",
            "Juez 02 familia municipal Cali",
            "Juez 03 familia municipal Cali",
            "Juez 04 familia municipal Cali",
            "Juez 05 familia municipal Cali",
            "Juez 06 familia municipal Cali",
            "Juez 01 familia circuito Cali",
            "Juez 02 familia circuito Cali",
            "Juez 03 familia circuito Cali",
            "Juez 04 familia circuito Cali",
            "Juez 05 familia circuito Cali",
            "Juez 06 familia circuito Cali",
            "Juez 01 familia municipal Buga",
            "Juez 02 familia municipal Buga",
            "Juez 03 familia municipal Buga",
            "Juez 04 familia municipal Buga",
            "Juez 01 familia circuito Buga",
            "Juez 02 familia circuito Buga",
            "Juez 03 familia circuito Buga",
            "Juez 04 familia circuito Buga"         
        ]
    },
    {  
        "id":3,
        "tipo_despacho":"Laboral",
        "nombre_despacho":[  
            "Juez 01 laboral municipal Palmira",
            "Juez 02 laboral municipal Palmira",
            "Juez 03 laboral municipal Palmira",
            "Juez 04 laboral municipal Palmira",
            "Juez 05 laboral municipal Palmira",
            "Juez 06 laboral municipal Palmira",
            "Juez 01 laboral circuito Palmira",
            "Juez 02 laboral circuito Palmira",
            "Juez 03 laboral circuito Palmira",
            "Juez 04 laboral circuito Palmira",
            "Juez 05 laboral circuito Palmira",
            "Juez 06 laboral circuito Palmira",
            "Juez 01 laboral municipal Cali",
            "Juez 02 laboral municipal Cali",
            "Juez 03 laboral municipal Cali",
            "Juez 04 laboral municipal Cali",
            "Juez 05 laboral municipal Cali",
            "Juez 06 laboral municipal Cali",
            "Juez 01 laboral circuito Cali",
            "Juez 02 laboral circuito Cali",
            "Juez 03 laboral circuito Cali",
            "Juez 04 laboral circuito Cali",
            "Juez 05 laboral circuito Cali",
            "Juez 06 laboral circuito Cali",
            "Juez 01 laboral municipal Cali",
            "Juez 02 laboral municipal Cali",
            "Juez 03 laboral municipal Cali",
            "Juez 04 laboral municipal Cali",
            "Juez 05 laboral municipal Cali",
            "Juez 06 laboral municipal Cali",
            "Juez 01 laboral circuito Cali",
            "Juez 02 laboral circuito Cali",
            "Juez 03 laboral circuito Cali",
            "Juez 04 laboral circuito Cali",
            "Juez 05 laboral circuito Cali",
            "Juez 06 laboral circuito Cali",
            "Juez 01 laboral municipal Buga",
            "Juez 02 laboral municipal Buga",
            "Juez 03 laboral municipal Buga",
            "Juez 04 laboral municipal Buga",
            "Juez 01 laboral circuito Buga",
            "Juez 02 laboral circuito Buga",
            "Juez 03 laboral circuito Buga",
            "Juez 04 laboral circuito Buga"         
        ]
    },{  
        "id":4,
        "tipo_despacho":"Administrativo",
        "nombre_despacho":[  
            "Juez 01 administrativo municipal Palmira",
            "Juez 02 administrativo municipal Palmira",
            "Juez 03 administrativo municipal Palmira",
            "Juez 04 administrativo municipal Palmira",
            "Juez 05 administrativo municipal Palmira",
            "Juez 06 administrativo municipal Palmira",
            "Juez 01 administrativo circuito Palmira",
            "Juez 02 administrativo circuito Palmira",
            "Juez 03 administrativo circuito Palmira",
            "Juez 04 administrativo circuito Palmira",
            "Juez 05 administrativo circuito Palmira",
            "Juez 06 administrativo circuito Palmira",
            "Juez 01 administrativo municipal Cali",
            "Juez 02 administrativo municipal Cali",
            "Juez 03 administrativo municipal Cali",
            "Juez 04 administrativo municipal Cali",
            "Juez 05 administrativo municipal Cali",
            "Juez 06 administrativo municipal Cali",
            "Juez 01 administrativo circuito Cali",
            "Juez 02 administrativo circuito Cali",
            "Juez 03 administrativo circuito Cali",
            "Juez 04 administrativo circuito Cali",
            "Juez 05 administrativo circuito Cali",
            "Juez 06 administrativo circuito Cali",
            "Juez 01 administrativo municipal Cali",
            "Juez 02 administrativo municipal Cali",
            "Juez 03 administrativo municipal Cali",
            "Juez 04 administrativo municipal Cali",
            "Juez 05 administrativo municipal Cali",
            "Juez 06 administrativo municipal Cali",
            "Juez 01 administrativo circuito Cali",
            "Juez 02 administrativo circuito Cali",
            "Juez 03 administrativo circuito Cali",
            "Juez 04 administrativo circuito Cali",
            "Juez 05 administrativo circuito Cali",
            "Juez 06 administrativo circuito Cali",
            "Juez 01 administrativo municipal Buga",
            "Juez 02 administrativo municipal Buga",
            "Juez 03 administrativo municipal Buga",
            "Juez 04 administrativo municipal Buga",
            "Juez 01 administrativo circuito Buga",
            "Juez 02 administrativo circuito Buga",
            "Juez 03 administrativo circuito Buga",
            "Juez 04 administrativo circuito Buga"         
        ]
    },
    {  
        "id":5,
        "tipo_despacho":"Promiscuo",
        "nombre_despacho":[  
            "Juez 01 promiscuo municipal Florida",
            "Juez 02 promiscuo municipal Florida",
            "Juez 01 promiscuo municipal Pradera",
            "Juez 01 promiscuo municipal Candelaria",
            "Juez 02 promiscuo municipal Candelaria",
            "Juez 03 promiscuo municipal Candelaria",
            "Juez 01 promiscuo municipal Cerrito",
            "Juez 02 promiscuo municipal Cerrito",
            "Juez 01 promiscuo municipal jamundi",
            "Juez 02 promiscuo municipal jamundi"

        ]
    },
    {  
        "id":6,
        "tipo_despacho":"Fiscalia",
        "nombre_despacho":[  
            "loCAS  01",
            "loCAS  02",
            "loCAS  03",
            "loCAS  04",
            "loCAS  05",
            "loCAS  06",
            "loCAS  07",
            "loCAS  08",
            "loCAS  09",
            "loCAS  10",
            "loCAS  11",
            "loCAS  12",
            "loCAS  13",
            "loCAS  14",
            "loCAS  15",
            "loCAS  16",
            "loCAS  17",
            "loCAS  18",
            "loCAS  19",
            "loCAS  20",
            "loCAS  21",
            "loCAS  22",
            "loCAS  23",
            "loCAS  24",
            "loCAS  25",
            "loCAS  26",
            "loCAS  27",
            "loCAS  28",
            "loCAS  29",
            "loCAS  30",
            "loCAS  31",
            "loCAS  32",
            "loCAS  33",
            "loCAS  34",
            "loCAS  35",
            "loCAS  36",
            "loCAS  37",
            "loCAS  38",
            "loCAS  39",
            "loCAS  40",
            "Seccional 01",
            "Seccional 02",
            "Seccional 03",
            "Seccional 04",
            "Seccional 05",
            "Seccional 06",
            "Seccional 07",
            "Seccional 08",
            "Seccional 09",
            "Seccional 10",
            "Seccional 11",
            "Seccional 12",
            "Seccional 13",
            "Seccional 14",
            "Seccional 15",
            "Seccional 16",
            "Seccional 17",
            "Seccional 18",
            "Seccional 19",
            "Seccional 20",
            "Seccional 21",
            "Seccional 22",
            "Seccional 23",
            "Seccional 24",
            "Seccional 25",
            "Seccional 26",
            "Seccional 27",
            "Seccional 28",
            "Seccional 29",
            "Seccional 30",
            "Seccional 31",
            "Seccional 32",
            "Seccional 33",
            "Seccional 34",
            "Seccional 35",
            "Seccional 36",
            "Seccional 37",
            "Seccional 38",
            "Seccional 39",
            "Seccional 40"  
        ]
    },
    {  
        "id":7,
        "tipo_despacho":"Entes Territoriales",
        "nombre_despacho":[  
            "Alcaldia secretaria",
            "Gobernaciones secretarias",
            "Ministerios",
            "Camaras comercio",
            "Notarias",
            "Superintendencias"
        ]
    },
    {  
        "id":8,
        "tipo_despacho":"Ejecucion de Penas",
        "nombre_despacho":[  
            "Juez 01 ejecucion de penas Palmira",
            "Juez 02 ejecucion de penas Palmira",
            "Juez 03 ejecucion de penas Palmira",
            "Juez 04 ejecucion de penas Palmira",
            "Juez 01 ejecucion de penas Cali",
            "Juez 02 ejecucion de penas Cali",
            "Juez 03 ejecucion de penas Cali",
            "Juez 04 ejecucion de penas Cali",
            "Juez 05 ejecucion de penas Cali",
            "Juez 06 ejecucion de penas Cali",
            "Juez 01 ejecucion de penas Buga",
            "Juez 02 ejecucion de penas Buga",
            "Juez 03 ejecucion de penas Buga",
            "Juez 04 ejecucion de penas Buga",
            "Juez 05 ejecucion de penas Buga",
            "Juez 04 ejecucion de penas Buga"
        ]
    }
]